<?xml version="1.0" encoding="UTF-8"?>
<con:soapui-project id="02792942-74bf-4d94-9ba6-386fefb1c2b2" created="3.30.0" activeEnvironment="Default environment" name="ProjectAPI" updated="3.30.0 2022-03-16T13:04:41Z" encryptionMode="Not encrypted" xmlns:con="http://eviware.com/soapui/config">
  <con:settings/>
  <con:interface xsi:type="con:RestService" id="018286ec-0582-4b42-9bf3-32fd8110d041" wadlVersion="http://wadl.dev.java.net/2009/02" name="https://api.github.com" type="rest" xmlns:xsi="http://www.w3.org/2001/XMLSchema-instance">
    <con:settings/>
    <con:definitionCache/>
    <con:endpoints>
      <con:endpoint>https://api.github.com</con:endpoint>
    </con:endpoints>
    <con:resource name="Emails" path="/user/emails" id="4f463c1e-d165-419d-b5b5-b09332efc4e1">
      <con:settings/>
      <con:parameters/>
      <con:method name="Emails" id="3f802e14-5d71-4573-b35f-c8398d6213f1" method="GET">
        <con:settings/>
        <con:parameters/>
        <con:representation type="FAULT">
          <con:mediaType>application/json; charset=utf-8</con:mediaType>
          <con:status>401</con:status>
          <con:params/>
          <con:element xmlns:ema="https://api.github.com/user/emails">ema:Fault</con:element>
        </con:representation>
        <con:representation type="RESPONSE">
          <con:mediaType>application/json; charset=utf-8</con:mediaType>
          <con:status>200</con:status>
          <con:params/>
          <con:element>Response</con:element>
        </con:representation>
        <con:request name="Request 1" id="32b220ce-0c50-45a4-9dc1-dec23cd92bdb" mediaType="application/json">
          <con:settings/>
          <con:endpoint>https://api.github.com</con:endpoint>
          <con:credentials>
            <con:selectedAuthProfile>No Authorization</con:selectedAuthProfile>
            <con:authType>No Authorization</con:authType>
          </con:credentials>
          <con:parameters/>
        </con:request>
      </con:method>
    </con:resource>
    <con:resource name="Keys" path="/user/keys" id="ab242719-0c07-46eb-b7ca-4c67c4fb1948">
      <con:settings/>
      <con:parameters/>
      <con:method name="Keys" id="55f7a53b-21d3-4621-a3dd-f8091ebf204c" method="POST">
        <con:settings/>
        <con:parameters/>
        <con:representation type="REQUEST">
          <con:mediaType>application/json</con:mediaType>
          <con:params/>
        </con:representation>
        <con:representation type="FAULT">
          <con:mediaType>application/json; charset=utf-8</con:mediaType>
          <con:status>401</con:status>
          <con:params/>
          <con:element xmlns:keys="https://api.github.com/user/keys">keys:Fault</con:element>
        </con:representation>
        <con:representation type="RESPONSE">
          <con:mediaType>application/json; charset=utf-8</con:mediaType>
          <con:status>201</con:status>
          <con:params/>
          <con:element xmlns:keys="https://api.github.com/user/keys">keys:Response</con:element>
        </con:representation>
        <con:request name="Request 1" id="998c2327-9d50-4fc4-ad5e-9651c0b28006" mediaType="application/json">
          <con:settings/>
          <con:endpoint>https://api.github.com</con:endpoint>
          <con:credentials>
            <con:selectedAuthProfile>No Authorization</con:selectedAuthProfile>
            <con:authType>No Authorization</con:authType>
          </con:credentials>
          <con:parameters/>
        </con:request>
      </con:method>
    </con:resource>
    <con:resource name="KeyId" path="/user/keys/{keyId}" id="053ef13d-3a90-4ae5-a3e0-66320dfdb672">
      <con:settings/>
      <con:parameters/>
      <con:method name="KeyId" id="6bb059cf-1520-4e0d-9edf-64121605c772" method="DELETE">
        <con:settings/>
        <con:parameters>
          <con:parameter required="true">
            <con:name>keyId</con:name>
            <con:value>keyId</con:value>
            <con:style>TEMPLATE</con:style>
            <con:default>keyId</con:default>
            <con:path xsi:nil="true"/>
            <con:description xsi:nil="true"/>
          </con:parameter>
        </con:parameters>
        <con:representation type="FAULT">
          <con:mediaType>application/json; charset=utf-8</con:mediaType>
          <con:status>401 404</con:status>
          <con:params/>
          <con:element xmlns:key="https://api.github.com/user/keys/keyId">key:Fault</con:element>
        </con:representation>
        <con:representation type="REQUEST">
          <con:mediaType>application/json</con:mediaType>
          <con:params/>
        </con:representation>
        <con:representation type="RESPONSE">
          <con:mediaType xsi:nil="true"/>
          <con:status>204</con:status>
          <con:params/>
          <con:element>data</con:element>
        </con:representation>
        <con:request name="Request 1" id="bec68c48-c7ff-43c4-8bbf-b76417934528" mediaType="application/json">
          <con:settings/>
          <con:endpoint>https://api.github.com</con:endpoint>
          <con:credentials>
            <con:selectedAuthProfile>No Authorization</con:selectedAuthProfile>
            <con:authType>No Authorization</con:authType>
          </con:credentials>
          <con:parameters>
            <con:entry key="keyId" value="keyId"/>
          </con:parameters>
          <con:parameterOrder>
            <con:entry>keyId</con:entry>
          </con:parameterOrder>
        </con:request>
      </con:method>
    </con:resource>
  </con:interface>
  <con:testSuite id="8fcf948d-61d6-4936-9032-ccec0cf8db13" name="GitHubTest">
    <con:settings/>
    <con:runType>SEQUENTIAL</con:runType>
    <con:testCase id="0791ad54-da60-4cc8-8a2e-abe359ef82a9" discardOkResults="false" failOnError="true" failTestCaseOnErrors="true" keepSession="false" name="Test Case" searchProperties="true" timeout="0">
      <con:settings/>
      <con:testStep type="restrequest" name="GET" id="c6d05c50-5ac7-42ca-977f-6609fe5cbfa3">
        <con:settings/>
        <con:config service="https://api.github.com" resourcePath="/user/emails" methodName="Emails" xsi:type="con:RestRequestStep" xmlns:xsi="http://www.w3.org/2001/XMLSchema-instance">
          <con:restRequest name="GET" id="32b220ce-0c50-45a4-9dc1-dec23cd92bdb" mediaType="application/json">
            <con:settings>
              <con:setting id="com.eviware.soapui.impl.wsdl.WsdlRequest@request-headers">&lt;xml-fragment/></con:setting>
            </con:settings>
            <con:endpoint>https://api.github.com</con:endpoint>
            <con:request/>
            <con:originalUri>https://api.github.com/user/emails</con:originalUri>
            <con:assertion type="Valid HTTP Status Codes" id="f0511c50-37d7-4203-b339-d1aedc098b43" name="Valid HTTP Status Codes">
              <con:settings/>
              <con:configuration>
                <codes>200</codes>
              </con:configuration>
            </con:assertion>
            <con:credentials>
              <con:selectedAuthProfile>GitHubAuth</con:selectedAuthProfile>
              <con:authType>No Authorization</con:authType>
            </con:credentials>
            <con:jmsConfig JMSDeliveryMode="PERSISTENT"/>
            <con:parameters/>
          </con:restRequest>
        </con:config>
      </con:testStep>
      <con:testStep type="restrequest" name="POST" id="9e2fade2-c31d-4c2c-af79-0508950edeec">
        <con:settings/>
        <con:config service="https://api.github.com" resourcePath="/user/keys" methodName="Keys" xsi:type="con:RestRequestStep" xmlns:xsi="http://www.w3.org/2001/XMLSchema-instance">
          <con:restRequest name="POST" id="998c2327-9d50-4fc4-ad5e-9651c0b28006" mediaType="application/json" postQueryString="false">
            <con:settings>
              <con:setting id="com.eviware.soapui.impl.wsdl.WsdlRequest@request-headers">&lt;xml-fragment/></con:setting>
            </con:settings>
            <con:endpoint>https://api.github.com</con:endpoint>
            <con:request>{
    "title": "TestAPIKey",
    "key": "ssh-rsa AAAAB3NzaC1yc2EAAAADAQABAAABgQDGBx6vVj1ahehMhxXN9ptz2dH/shln0GDON90UHCLdYRI7DoWmvDUF1TvBNwSJxe1ApHmWpZfpBaWgn2BtD8nqorWLgSiflJv/FHlVw3OzrxHHvE1wJgH5C+MHETpt1gAPaSCd0zuToF23KZCvKThus5eY5TLdhtbJ80aGuwuteL1NRXnjHtEhgRj7RRYHlhcCvdY3RwceywNWU007iK1gD9Za572hAbqHCw9UcwILtUNRJ4RnHSwIS6IDyV9MWpmz9TFw9rhjbm3YNLK5Svcv5x7rp5Ox3Rq++e6ipOkGPSRcDnsCUnFBaNX2FHc5LNoQfQhafWZ2U4LEqlaKneTr1wwTJ13h5Z8+l0CHQ5Xfdckt70R1kLdqDNLYJdw1nOvZahaBRhleRz+CiEL4HzlUS8fECdP0XsPS/pAFXWIWJCQGx5KVY7CiX6es694qHdR7QNU8GiReyCyES+IeOCUveehflo0S7kuqmBBR0fKFKKf3jMSq+5Ky+h9KTA7GgJ8="
}</con:request>
            <con:originalUri>https://api.github.com/user/keys</con:originalUri>
            <con:assertion type="Valid HTTP Status Codes" id="06fcbcf8-f0dc-4769-95a6-413deb8fd154" name="Valid HTTP Status Codes">
              <con:settings/>
              <con:configuration>
                <codes>201</codes>
              </con:configuration>
            </con:assertion>
            <con:credentials>
              <con:selectedAuthProfile>GitHubAuth</con:selectedAuthProfile>
              <con:authType>No Authorization</con:authType>
            </con:credentials>
            <con:jmsConfig JMSDeliveryMode="PERSISTENT"/>
            <con:parameters/>
          </con:restRequest>
        </con:config>
      </con:testStep>
      <con:testStep type="transfer" name="Property Transfer" id="1a3b0166-7e48-4102-8c51-b3a0a6c5b23c">
        <con:settings/>
        <con:config xsi:type="con:PropertyTransfersStep" xmlns:xsi="http://www.w3.org/2001/XMLSchema-instance">
          <con:transfers setNullOnMissingSource="true" transferTextContent="true" failOnError="true" ignoreEmpty="false" transferToAll="false" entitize="false" transferChildNodes="false">
            <con:name>transfer1</con:name>
            <con:sourceType>Response</con:sourceType>
            <con:sourceStep>POST</con:sourceStep>
            <con:sourcePath>$['id']</con:sourcePath>
            <con:targetType>keyId</con:targetType>
            <con:targetStep>DELETE</con:targetStep>
            <con:targetPath/>
            <con:type>JSONPATH</con:type>
            <con:targetTransferType>XPATH</con:targetTransferType>
            <con:upgraded>true</con:upgraded>
          </con:transfers>
        </con:config>
      </con:testStep>
      <con:testStep type="restrequest" name="DELETE" id="375dba22-1272-4b21-8917-a9fd92ebb77b">
        <con:settings/>
        <con:config service="https://api.github.com" resourcePath="/user/keys/{keyId}" methodName="KeyId" xsi:type="con:RestRequestStep" xmlns:xsi="http://www.w3.org/2001/XMLSchema-instance">
          <con:restRequest name="DELETE" id="bec68c48-c7ff-43c4-8bbf-b76417934528" mediaType="application/json" postQueryString="false">
            <con:settings>
              <con:setting id="com.eviware.soapui.impl.wsdl.WsdlRequest@request-headers">&lt;xml-fragment/></con:setting>
            </con:settings>
            <con:endpoint>https://api.github.com</con:endpoint>
            <con:request/>
            <con:originalUri>https://api.github.com/user/keys/keyId</con:originalUri>
            <con:assertion type="Valid HTTP Status Codes" id="53a3e8c4-3dae-4347-bc18-027efef16676" name="Valid HTTP Status Codes">
              <con:settings/>
              <con:configuration>
                <codes>204</codes>
              </con:configuration>
            </con:assertion>
            <con:credentials>
              <con:selectedAuthProfile>GitHubAuth</con:selectedAuthProfile>
              <con:authType>No Authorization</con:authType>
            </con:credentials>
            <con:jmsConfig JMSDeliveryMode="PERSISTENT"/>
            <con:parameters>
              <con:entry key="keyId" value="64646765"/>
            </con:parameters>
            <con:parameterOrder>
              <con:entry>keyId</con:entry>
            </con:parameterOrder>
          </con:restRequest>
        </con:config>
      </con:testStep>
      <con:properties/>
      <con:reportParameters/>
    </con:testCase>
    <con:properties/>
    <con:reportParameters/>
  </con:testSuite>
  <con:properties/>
  <con:wssContainer/>
  <con:databaseConnectionContainer/>
  <con:jmsConnectionContainer/>
  <con:oAuth2ProfileContainer>
    <con:oAuth2Profile>
      <con:name>GitHubAuth</con:name>
      <con:type>OAuth 2.0</con:type>
      <con:accessToken>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</con:accessToken>
      <con:accessTokenPosition>HEADER</con:accessTokenPosition>
      <con:accessTokenStartingStatus>ENTERED_MANUALLY</con:accessTokenStartingStatus>
      <con:oAuth2Flow>AUTHORIZATION_CODE_GRANT</con:oAuth2Flow>
      <con:refreshAccessTokenMethod>AUTOMATIC</con:refreshAccessTokenMethod>
      <con:jwtConfiguration/>
      <con:responseType>id_token</con:responseType>
    </con:oAuth2Profile>
  </con:oAuth2ProfileContainer>
  <con:oAuth1ProfileContainer/>
  <con:reporting>
    <con:xmlTemplates/>
    <con:parameters/>
  </con:reporting>
  <con:eventHandlers type="RequestFilter.filterRequest" name="RequestFilter.filterRequest">
    <con:script>// Sample event script to add custom HTTP header to all outgoing REST, SOAP and HTTP(S) calls
// This code is often used for adding custom authentication to ReadyAPI functional tests

// If hardcoding the token, uncomment and change line 5
// token = '4567'

// If your token is parameterized in Project level custom property, uncomment line 8
// token = request.parent.testCase.testSuite.project.getProperty('auth_token').getValue()

// To modify all outgoing calls, remove comments from lines 11 to 16
// headers = request.requestHeaders
// if (headers.containsKey('auth_token2') == false) {
//   headers.put('auth_token2', token)
//   request.requestHeaders = headers
// }</con:script>
  </con:eventHandlers>
  <con:eventHandlers type="TestRunListener.afterStep" name="TestRunListener.afterStep">
    <con:script>// Save all test step results into files
// Change the directory path in line 5 to a location where you want to store details
// then uncomment lines 5 to 10

// filePath = 'C:\\tempOutputDirectory\\'
// fos = new java.io.FileOutputStream(filePath + testStepResult.testStep.label + '.txt', true)
// pw = new java.io.PrintWriter(fos)
// testStepResult.writeTo(pw)
// pw.close()
// fos.close()</con:script>
  </con:eventHandlers>
  <con:authRepository>
    <con:oAuth20AuthEntry>
      <con:name>GitHubAuth</con:name>
      <con:type>OAuth 2.0</con:type>
      <con:accessToken>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</con:accessToken>
      <con:accessTokenPosition>HEADER</con:accessTokenPosition>
      <con:accessTokenStartingStatus>ENTERED_MANUALLY</con:accessTokenStartingStatus>
      <con:oAuth2Flow>AUTHORIZATION_CODE_GRANT</con:oAuth2Flow>
      <con:refreshAccessTokenMethod>AUTOMATIC</con:refreshAccessTokenMethod>
      <con:jwtConfiguration/>
      <con:responseType>id_token</con:responseType>
    </con:oAuth20AuthEntry>
  </con:authRepository>
  <con:tags/>
</con:soapui-project>
